mesures/__init__.py
mesures/a5d.py
mesures/agrecl.py
mesures/almacenacau.py
mesures/autoconsumo.py
mesures/b5d.py
mesures/cilcau.py
mesures/cupscau.py
mesures/f1.py
mesures/headers.py
mesures/p1.py
mesures/p1d.py
mesures/p2.py
mesures/p2d.py
mesures/p5d.py
mesures/pmest.py
mesures/dates/__init__.py
mesures/dates/date.py
mesures/file_structs/__init__.py
mesures/file_structs/headers.py
mesures/parsers/__init__.py
mesures/parsers/dummy_data.py
mesures-1.4.5.dist-info/DESCRIPTION.rst
mesures-1.4.5.dist-info/METADATA
mesures-1.4.5.dist-info/RECORD
mesures-1.4.5.dist-info/WHEEL
mesures-1.4.5.dist-info/metadata.json
mesures-1.4.5.dist-info/top_level.txt
spec/__init__.py
spec/sample_data.py
tests/__init__.py
tests/sample_data.py
tests/test_f1.py
tests/test_p1.py
