Metadata-Version: 2.0
Name: mesures
Version: 1.4.5
Summary: Eina d'intercanvi fitxers de mesures REE
Home-page: https://github.com/gisce/mesures
Author: GISCE-TI S.L.
Author-email: devel@gisce.net
License: BSD 3-Clause License
Platform: UNKNOWN
Provides: mesures
Requires-Dist: expects
Requires-Dist: mamba (<0.11.0)
Requires-Dist: pandas (==0.23.4)
